[
    {
        "model": "core.product",
        "pk": 1,
        "fields": {
            "created_at": "2022-11-28T09:06:08.128Z",
            "updated_at": "2022-11-28T09:06:08.128Z",
            "name": "Lollipop Cardigan",
            "description": "คาร์ดิแกนรุ่นขายดีสุดสีใหม่🌿เขียวใบชา🌿ละมุนตุ้นน่ารักที่สุดค่า✨ เขียวนี้แมทช์ง่ายมากใส่กับอะไรก็เข้า รุ่นนี้ไม่เคยมีโทนนี้น้า นานๆทีจะมาค่า รีบสอยก่อนของหมดน้า 🙌🏻",
            "url": "https://www.instagram.com/p/CllfzVWJDJL/?utm_source=ig_web_copy_link",
            "status": "hot",
            "min_price": "380.00",
            "max_price": "500.00",
            "brand": 1,
            "promotion": null
        }
    }
]